pyopenhc-0.1.2.data/purelib/pyopenhc/__init__.py
pyopenhc-0.1.2.data/purelib/pyopenhc/libopencc.1.1.7.dylib
pyopenhc-0.1.2.data/purelib/pyopenhc/libopencc.1.1.dylib
pyopenhc-0.1.2.data/purelib/pyopenhc/libopencc.dylib
pyopenhc-0.1.2.data/purelib/pyopenhc/pyopenhc.py
pyopenhc-0.1.2.data/purelib/pyopenhc/data/HKVariants.ocd2
pyopenhc-0.1.2.data/purelib/pyopenhc/data/HKVariantsRev.ocd2
pyopenhc-0.1.2.data/purelib/pyopenhc/data/HKVariantsRevPhrases.ocd2
pyopenhc-0.1.2.data/purelib/pyopenhc/data/JPShinjitaiCharacters.ocd2
pyopenhc-0.1.2.data/purelib/pyopenhc/data/JPShinjitaiPhrases.ocd2
pyopenhc-0.1.2.data/purelib/pyopenhc/data/JPVariants.ocd2
pyopenhc-0.1.2.data/purelib/pyopenhc/data/JPVariantsRev.ocd2
pyopenhc-0.1.2.data/purelib/pyopenhc/data/STCharacters.ocd2
pyopenhc-0.1.2.data/purelib/pyopenhc/data/STPhrases.ocd2
pyopenhc-0.1.2.data/purelib/pyopenhc/data/TSCharacters.ocd2
pyopenhc-0.1.2.data/purelib/pyopenhc/data/TSPhrases.ocd2
pyopenhc-0.1.2.data/purelib/pyopenhc/data/TWPhrases.ocd2
pyopenhc-0.1.2.data/purelib/pyopenhc/data/TWPhrasesRev.ocd2
pyopenhc-0.1.2.data/purelib/pyopenhc/data/TWVariants.ocd2
pyopenhc-0.1.2.data/purelib/pyopenhc/data/TWVariantsRev.ocd2
pyopenhc-0.1.2.data/purelib/pyopenhc/data/TWVariantsRevPhrases.ocd2
pyopenhc-0.1.2.data/purelib/pyopenhc/data/hk2s.json
pyopenhc-0.1.2.data/purelib/pyopenhc/data/hk2t.json
pyopenhc-0.1.2.data/purelib/pyopenhc/data/jp2t.json
pyopenhc-0.1.2.data/purelib/pyopenhc/data/s2hk.json
pyopenhc-0.1.2.data/purelib/pyopenhc/data/s2t.json
pyopenhc-0.1.2.data/purelib/pyopenhc/data/s2tw.json
pyopenhc-0.1.2.data/purelib/pyopenhc/data/s2twp.json
pyopenhc-0.1.2.data/purelib/pyopenhc/data/t2hk.json
pyopenhc-0.1.2.data/purelib/pyopenhc/data/t2jp.json
pyopenhc-0.1.2.data/purelib/pyopenhc/data/t2s.json
pyopenhc-0.1.2.data/purelib/pyopenhc/data/t2tw.json
pyopenhc-0.1.2.data/purelib/pyopenhc/data/tw2s.json
pyopenhc-0.1.2.data/purelib/pyopenhc/data/tw2sp.json
pyopenhc-0.1.2.data/purelib/pyopenhc/data/tw2t.json
pyopenhc-0.1.2.dist-info/LICENSE
pyopenhc-0.1.2.dist-info/METADATA
pyopenhc-0.1.2.dist-info/WHEEL
pyopenhc-0.1.2.dist-info/top_level.txt
pyopenhc-0.1.2.dist-info/RECORD
