Metadata-Version: 2.1
Name: pyopenhc
Version: 0.1.2
Summary: PyOpenHC
Home-page: https://github.com/pengzhendong/pyopenhc
Author: Zhendong Peng
Author-email: pzd17@tsinghua.org.cn
Classifier: Programming Language :: Python :: 3
Classifier: Operating System :: OS Independent
Classifier: Topic :: Scientific/Engineering
License-File: LICENSE
